CONTRIBUTING.md
DESCRIPTION.md
LICENSE.txt
MANIFEST.in
NOTICE
README.md
SECURITY.md
pyproject.toml
setup.cfg
setup.py
src/snowflake/connector/__init__.py
src/snowflake/connector/_query_context_cache.py
src/snowflake/connector/_sql_util.py
src/snowflake/connector/arrow_context.py
src/snowflake/connector/arrow_iterator.pyx
src/snowflake/connector/azure_storage_client.py
src/snowflake/connector/bind_upload_agent.py
src/snowflake/connector/cache.py
src/snowflake/connector/compat.py
src/snowflake/connector/config_manager.py
src/snowflake/connector/connection.py
src/snowflake/connector/connection_diagnostic.py
src/snowflake/connector/constants.py
src/snowflake/connector/converter.py
src/snowflake/connector/converter_issue23517.py
src/snowflake/connector/converter_null.py
src/snowflake/connector/converter_snowsql.py
src/snowflake/connector/cursor.py
src/snowflake/connector/dbapi.py
src/snowflake/connector/description.py
src/snowflake/connector/encryption_util.py
src/snowflake/connector/errorcode.py
src/snowflake/connector/errors.py
src/snowflake/connector/feature.py
src/snowflake/connector/file_compression_type.py
src/snowflake/connector/file_transfer_agent.py
src/snowflake/connector/file_util.py
src/snowflake/connector/gcs_storage_client.py
src/snowflake/connector/gzip_decoder.py
src/snowflake/connector/local_storage_client.py
src/snowflake/connector/network.py
src/snowflake/connector/ocsp_asn1crypto.py
src/snowflake/connector/ocsp_snowflake.py
src/snowflake/connector/options.py
src/snowflake/connector/pandas_tools.py
src/snowflake/connector/proxy.py
src/snowflake/connector/py.typed
src/snowflake/connector/result_batch.py
src/snowflake/connector/result_set.py
src/snowflake/connector/s3_storage_client.py
src/snowflake/connector/secret_detector.py
src/snowflake/connector/sf_dirs.py
src/snowflake/connector/sfbinaryformat.py
src/snowflake/connector/sfdatetime.py
src/snowflake/connector/snow_logging.py
src/snowflake/connector/sqlstate.py
src/snowflake_connector_python_2.egg-info/PKG-INFO
src/snowflake_connector_python_2.egg-info/SOURCES.txt
src/snowflake_connector_python_2.egg-info/dependency_links.txt
src/snowflake_connector_python_2.egg-info/entry_points.txt
src/snowflake_connector_python_2.egg-info/not-zip-safe
src/snowflake_connector_python_2.egg-info/requires.txt
src/snowflake_connector_python_2.egg-info/top_level.txt